sphinxcontrib/__init__.py
sphinxcontrib/analyzers/__init__.py
sphinxcontrib/analyzers/base.py
sphinxcontrib/analyzers/javascript.py
sphinxcontrib/autoanysrc.py
sphinxcontrib_autoanysrc-0.2.0.dist-info/METADATA
sphinxcontrib_autoanysrc-0.2.0.dist-info/WHEEL
sphinxcontrib_autoanysrc-0.2.0.dist-info/RECORD
