Metadata-Version: 2.1
Name: sphinxcontrib-autoanysrc
Version: 0.2.0
Summary: Sphinx extension with some autodoc features for any sources
Home-page: https://github.com/sphinx-contrib/autoanysrc
License: BSD
Author: Evgeniy Tatarkin
Author-email: tatarkin.evg@gmail.com
Requires-Python: >=3.8,<4.0
Classifier: Environment :: Web Environment
Classifier: Framework :: Django
Classifier: Intended Audience :: Developers
Classifier: License :: OSI Approved :: BSD License
Classifier: License :: Other/Proprietary License
Classifier: Programming Language :: Python
Classifier: Programming Language :: Python :: 3
Classifier: Programming Language :: Python :: 3.8
Classifier: Programming Language :: Python :: 3.9
Classifier: Programming Language :: Python :: 3.10
Classifier: Programming Language :: Python :: 3.11
Classifier: Programming Language :: Python :: 3.12
Classifier: Topic :: Documentation
Classifier: Topic :: Utilities
Requires-Dist: Sphinx (>=1.6,<8.0)
Project-URL: Repository, https://github.com/sphinx-contrib/autoanysrc
